README
setup.cfg
setup.py
multiprocesspool/__init__.py
multiprocesspool/example1.py
multiprocesspool/example2.py
multiprocesspool/multiprocesspool.py
multiprocesspool.egg-info/PKG-INFO
multiprocesspool.egg-info/SOURCES.txt
multiprocesspool.egg-info/dependency_links.txt
multiprocesspool.egg-info/top_level.txt