Metadata-Version: 1.1
Name: multiprocesspool
Version: 0.0.1
Summary: Use multiples process to do operations on a list
Home-page: https://bitbucket.org/Astyan/processpool
Author: Astyan
Author-email: aurelien.vezin@etu.unistra.fr
License: CeCILL-B
Keywords: multi,process,pool
Platform: UNKNOWN
Classifier: Development Status :: 3 - Alpha
Classifier: Intended Audience :: Developers
Classifier: Topic :: Software Development :: Libraries :: Python Modules
Classifier: License :: OSI Approved
Classifier: Programming Language :: Python :: 2.7
Classifier: Operating System :: OS Independent
